stacchip/__init__.py
stacchip/chipper.py
stacchip/indexer.py
stacchip/utils.py
stacchip/processors/landsat_processor.py
stacchip/processors/linz_processor.py
stacchip/processors/modis_processor.py
stacchip/processors/naip_processor.py
stacchip/processors/prechip.py
stacchip/processors/sentinel_1_processor.py
stacchip/processors/sentinel_2_processor.py
stacchip/processors/stats.py
stacchip/processors/strategy.py
stacchip-0.1.38.dist-info/METADATA
stacchip-0.1.38.dist-info/WHEEL
stacchip-0.1.38.dist-info/entry_points.txt
stacchip-0.1.38.dist-info/licenses/LICENSE
stacchip-0.1.38.dist-info/RECORD
