Metadata-Version: 2.3
Name: stacchip
Version: 0.1.38
Summary: Dynamically create image chips from STAC items
Project-URL: Homepage, https://github.com/Clay-foundation/stacchip
Project-URL: Bug Tracker, https://github.com/Clay-foundation/stacchip/issues
Author-email: Daniel Wiesmann <danielwiesmann@developmentseed.org>
License-File: LICENSE
Requires-Python: >=3.10
Requires-Dist: boto3>=1.29.0
Requires-Dist: geoarrow-pyarrow>=0.1.2
Requires-Dist: geopandas>=0.14.1
Requires-Dist: numpy<2.0,>=1.26.0
Requires-Dist: planetary-computer>=1.0.0
Requires-Dist: pyarrow>=14.0.1
Requires-Dist: pystac-client>=0.7.5
Requires-Dist: pystac>=1.9.0
Requires-Dist: rasterio>=1.3.9
Requires-Dist: rio-stac>=0.9.0
Provides-Extra: dev
Requires-Dist: build; extra == 'dev'
Requires-Dist: mock; extra == 'dev'
Requires-Dist: pytest; extra == 'dev'
Requires-Dist: ruff; extra == 'dev'
Requires-Dist: types-python-dateutil; extra == 'dev'
Provides-Extra: docs
Requires-Dist: mkdocs; extra == 'docs'
Requires-Dist: mkdocs-jupyter; extra == 'docs'
Requires-Dist: mkdocs-material; extra == 'docs'
Requires-Dist: nbconvert; extra == 'docs'
Requires-Dist: pdocs; extra == 'docs'
Requires-Dist: pygments; extra == 'docs'
